<?xml version="1.0" encoding="utf-8"?>
<reviews><review><image>https://scontent.fsdv2-1.fna.fbcdn.net/v/t1.0-1/c0.0.976.976a/s200x200/66720866_10216941907992302_7685248393077063680_o.jpg?_nc_cat=100&amp;_nc_oc=AQlZVnemEczAqbPW18waXq8VCt880tDkyGsR_FdxFOKYASZNxl6JQPE8V45thJEY8Cg&amp;_nc_ht=scontent.fsdv2-1.fna&amp;oh=647f902cc870c3f1ea42d78f544601e1&amp;oe=5ED95D7A</image><name>Hili Yalon</name><comment>וואו מדהים חוויה אני הרגשתי בידיים טובות ובטוחה ושינוי מיידי    תודה תודה תודה</comment></review><review><image>https://scontent.fsdv2-1.fna.fbcdn.net/v/t1.0-1/p200x200/82580961_10162843599390147_489903876955176960_n.jpg?_nc_cat=106&amp;_nc_oc=AQkK5LdYZZtAjKw1W2TWRXL216eqa5iwQiqXCDqYOfdSe09Zpx3BZA-M_5XlZRCit6k&amp;_nc_ht=scontent.fsdv2-1.fna&amp;_nc_tp=6&amp;oh=20b334a4f236da7b1c8b08356189c272&amp;oe=5EB8957F</image><name>Sivan Talmor</name><comment>הילה העניקה לי טיפול מ פ נ ק ומוצלח ! ברוך ועדינות , עם תכשירים שפינקו לי את עור הפנים. ממליצה בחום 
                                </comment></review><review><image>https://scontent.fsdv2-1.fna.fbcdn.net/v/t1.0-1/p200x200/11817178_10206028210238679_131643860468915283_n.jpg?_nc_cat=109&amp;_nc_oc=AQm3PyoATgL0ycRA2zWaOe6wXZL8LnDNN_WtzCDkfEVHk0Qk8laZCa1xB9Y0sLR-0k8&amp;_nc_ht=scontent.fsdv2-1.fna&amp;_nc_tp=6&amp;oh=d5dcc4d3b9439c263a38a00b76264879&amp;oe=5EC6BFE5</image><name>Danielle Yaari</name><comment>ממליצה בחום מנסיון אישי! מודה שלא נתתי לאף אחת לגעת לי בפנים חוץ מהילה! טיפול אישי ומסור מלא בכל טוב שבאמת רואים אחריו הבדל משמעותי בפנים! תודה לך אהובה יש לך ידיי זהב
                            </comment></review><review><image>https://scontent.fsdv2-1.fna.fbcdn.net/v/t1.0-1/p200x200/60959914_2419358061449482_6430493450105257984_o.jpg?_nc_cat=102&amp;_nc_oc=AQmHhzLo5LzaaqHJWjoN1rHH9Q-y_GMMtmnLEUfWNxDx-xSCULz1G3Go7YgoDq4Hu80&amp;_nc_ht=scontent.fsdv2-1.fna&amp;_nc_tp=6&amp;oh=e654680bd6d79a9e3d033fe12178bbf1&amp;oe=5EC8421B</image><name>Naama Feuerstein</name><comment>שפע של מקצועיות , אהבה ודיוק. אין על הילה בכל המובנים. מי שמחפש/ת טיפול מקוצועי , נעים והכי חשוב עם תוצאות מדהימות הילה היא הכתובת 
                            </comment></review><review><image>https://scontent.fsdv2-1.fna.fbcdn.net/v/t1.0-1/p200x200/56472514_2254209777933217_5712367814338150400_o.jpg?_nc_cat=110&amp;_nc_oc=AQkjw3MHxw4B3iNNc0p8YX6a-FVXkutRvkPO1bF9R8XgiNHayB3vb0up-A1IONu2RoM&amp;_nc_ht=scontent.fsdv2-1.fna&amp;_nc_tp=6&amp;oh=ab0a1efe2d4605b1b925e886c32d9cd8&amp;oe=5ED92813</image><name>Doria Catane Segal</name><comment>ממליצה בחום מניסיון אישי
                            </comment></review><review><image>https://scontent.fsdv2-1.fna.fbcdn.net/v/t1.0-1/p200x200/61400835_2513890898624131_2564962324666384384_n.jpg?_nc_cat=107&amp;_nc_oc=AQnw2rZhbhfSx24jT-Lgx75KB_fHICcO2JlmGSuNNhCylHQhwkxepcJqTtMT_HGiPq4&amp;_nc_ht=scontent.fsdv2-1.fna&amp;_nc_tp=6&amp;oh=8969299cbfbdcf4a97d6c204ce0affaa&amp;oe=5EDAE604</image><name>Mazal Yakobi</name><comment>תודה על הטיפול המסור והנעים, ניכר כי את אוהבת את התחום ומקצועית מאוד. הרגשתי שאני בידיים טובות 
                            </comment></review><review><image>https://scontent.fsdv2-1.fna.fbcdn.net/v/t1.0-1/p200x200/71347624_10211146249611706_8756762658058797056_n.jpg?_nc_cat=107&amp;_nc_oc=AQkRMO0pa25sjfyBkzMLKTKKPBfgFHSCawgha9ahK4q_z4fc1fiOclJSA3nEppDQDUs&amp;_nc_ht=scontent.fsdv2-1.fna&amp;_nc_tp=6&amp;oh=0f20ac84b87190f6ce04471741856979&amp;oe=5EDBE490</image><name>Tzippy Weiss Post</name><comment>הילה מהממת מפנקת מאוד! יצאתי עם עור זורח  וכיף לדעת שהכל טבעי ממליצה בחום</comment></review><review><image>https://scontent.fsdv2-1.fna.fbcdn.net/v/t1.0-1/p200x200/71303390_2681870831852721_2116720532425539584_o.jpg?_nc_cat=110&amp;_nc_oc=AQkvPed1i-UF8EBBHwefGboa_K8NgzZ-B1aZ52Znvnoc6heqoENXq_brgMuRCGW67BY&amp;_nc_ht=scontent.fsdv2-1.fna&amp;_nc_tp=6&amp;oh=5ac9c100c995f0cd355b717c677f68d2&amp;oe=5EC70070</image><name>Lilu Popov Levi</name><comment>תודה הילה יקרה על הטיפול המפנק! המסכות שרקחת היו מדהימות ..וגם הדיקור!!! תודה על התפריט המיוחד והנכון!</comment></review><review><image>https://scontent.fsdv2-1.fna.fbcdn.net/v/t1.0-1/p200x200/38668259_1863270503753315_5154537646617264128_o.jpg?_nc_cat=103&amp;_nc_oc=AQneQU-v8VvJeJ7JfL-crMlwZsGIrD9UYh_OjLMPZQ_hstrpaeocHzAZko4lAuJjmNw&amp;_nc_ht=scontent.fsdv2-1.fna&amp;_nc_tp=6&amp;oh=9245f9cc5f30f7569c34ba9fa790c6ca&amp;oe=5ED92230</image><name>גבי סולומון</name><comment>הייתי אתמול בטיפול פנים אצל הילה. הטיפול כלל הרבה מעבר לטיפול פנים;  דברנו על תזונה מתאימה ושנוי קל של אורח החיים. הטיפול עצמו היה נעים ומרגיע . הילה נעימה ומכבדת 
                                </comment></review><review><image>https://scontent.fsdv2-1.fna.fbcdn.net/v/t1.0-1/p200x200/13346901_1045389465535609_3074745706532311506_n.jpg?_nc_cat=107&amp;_nc_oc=AQnCgGMKJzy0BWgxbnJ7dwS3RcCDa_gbVDNmTcXO7z2R1DHYCj_f7IQvb7kpgpHfVL8&amp;_nc_ht=scontent.fsdv2-1.fna&amp;_nc_tp=6&amp;oh=98b25f7ce2d0a753f9cc2d4f01df3f8a&amp;oe=5EDB264F</image><name>Odelia Mordechai</name><comment>אחרי טיפול ארוך הכולל שינוי תזונתי וטיפולי פנים - יש תוצאות! מומלץ בחום
                            </comment></review><review><image>https://scontent.fsdv2-1.fna.fbcdn.net/v/t1.0-1/c0.0.200.200a/p200x200/83515640_2696527763762343_7721841166546632704_o.jpg?_nc_cat=104&amp;_nc_oc=AQk8pgBhUYxZP49ef_T_HHDSxKSaguf5CqRm6246nXFp0rrIcJNLcXXERwjEXSl-qFM&amp;_nc_ht=scontent.fsdv2-1.fna&amp;oh=0726edc02d432f0b8606c5e31ceb074d&amp;oe=5ED5335B</image><name>Shiri Rolider</name><comment>פעם ראשונה שאני עושה טיפול פנים יצאתי הכי מרוצה תוצאות מדהימות הילה מקצועית ונעימה!! ממליצה ממליצה!!
                            </comment></review><review><image>https://scontent.fsdv2-1.fna.fbcdn.net/v/t1.0-1/c32.0.200.200a/p200x200/71408752_2665148233549509_6262266543262924800_o.jpg?_nc_cat=102&amp;_nc_oc=AQn_g3_tD5iHe6XlDpkMV-uEyTczwwB6v0xAPyugJK5DIMIqZfbkyItw_iVncIOp-yc&amp;_nc_ht=scontent.fsdv2-1.fna&amp;oh=02e3565484b495e43e535c4feb401af5&amp;oe=5EC42A87</image><name>Eyal Babajani</name><comment>הילה פשוט מקצוענית בחסד עליון. שולטת היטב ברזי מקצוע הנטורופתיה והדיקור. היא ישרה, הגונה, מסורה וקשובה. מעבר לכך פשוט אישה מקסימה. תצאו סופר מרוצים מהטיפול אצלה. באחריות:). מומלץ בחום רב חברים! 
                            </comment></review></reviews>
